trisicell-0.2.3.dist-info/dependency_links.txt
trisicell-0.2.3.dist-info/WHEEL
trisicell-0.2.3.dist-info/LICENSE
trisicell-0.2.3.dist-info/RECORD
trisicell-0.2.3.dist-info/entry_points.txt
trisicell-0.2.3.dist-info/top_level.txt
trisicell-0.2.3.dist-info/METADATA
trisicell/__init__.py
trisicell/settings/_settings.py
trisicell/settings/__init__.py
trisicell/io/_genotype.py
trisicell/io/_tree.py
trisicell/io/__init__.py
trisicell/external/_mltd.cpp
trisicell/external/_mp3.py
trisicell/external/_scite.cpython-39-x86_64-linux-gnu.so
trisicell/external/_scprob.cpp
trisicell/external/_betabinom.py
trisicell/external/_scistree.pyx
trisicell/external/_scprob.cpython-39-x86_64-linux-gnu.so
trisicell/external/_scistree.cpython-39-x86_64-linux-gnu.so
trisicell/external/__init__.py
trisicell/external/_scistree.cpp
trisicell/external/_mltd.pyx
trisicell/external/_scite.cpp
trisicell/external/_scite.pyx
trisicell/external/_scprob.pyx
trisicell/external/_mltd.cpython-39-x86_64-linux-gnu.so
trisicell/external/mltd/mltd.h
trisicell/external/mltd/mltd.cpp
trisicell/external/scistree/RBT.h
trisicell/external/scistree/PhylogenyTreeBasic.h
trisicell/external/scistree/BinaryMatrix.cpp
trisicell/external/scistree/ScistErrRateInf.cpp
trisicell/external/scistree/Utils2.h
trisicell/external/scistree/ctpl_stl.h
trisicell/external/scistree/main.cpp
trisicell/external/scistree/main.h
trisicell/external/scistree/Utils2.cpp
trisicell/external/scistree/ScistPerfPhyImp.hpp
trisicell/external/scistree/ScistPerfPhyUtils.hpp
trisicell/external/scistree/BinaryMatrix.h
trisicell/external/scistree/PhylogenyTree.h
trisicell/external/scistree/ScistPerfPhyUtils.cpp
trisicell/external/scistree/UnWeightedGraph.h
trisicell/external/scistree/Utils.cpp
trisicell/external/scistree/PhylogenyTree.cpp
trisicell/external/scistree/ScistPerfPhyImp.cpp
trisicell/external/scistree/UtilsNumerical.cpp
trisicell/external/scistree/TreeBuilder.cpp
trisicell/external/scistree/ScistGenotype.cpp
trisicell/external/scistree/MarginalTree.h
trisicell/external/scistree/BioSequenceMatrix.h
trisicell/external/scistree/RerootTreeUtils.h
trisicell/external/scistree/MarginalTree.cpp
trisicell/external/scistree/Utils4.h
