Metadata-Version: 2.1
Name: trisicell
Version: 0.2.3
Summary: UNKNOWN
Home-page: https://github.com/faridrashidi/trisicell
Author: Farid Rashidi
Author-email: farid.rsh@gmail.com
Maintainer: Farid Rashidi
Maintainer-email: farid.rsh@gmail.com
License: BSD
Download-URL: https://github.com/faridrashidi/trisicell
Project-URL: Documentation, https://trisicell.readthedocs.io/en/latest
Project-URL: Source Code, https://github.com/faridrashidi/trisicell
Keywords: tumor phylogeny,single cell,scalable,rna-seq,dna-seq
Platform: Linux
Platform: MacOSX
Classifier: License :: OSI Approved :: BSD License
Classifier: Development Status :: 5 - Production/Stable
Classifier: Intended Audience :: Developers
Classifier: Intended Audience :: Science/Research
Classifier: Natural Language :: English
Classifier: Framework :: Jupyter
Classifier: Operating System :: MacOS :: MacOS X
Classifier: Operating System :: Microsoft :: Windows
Classifier: Operating System :: POSIX :: Linux
Classifier: Programming Language :: Python :: 3
Classifier: Programming Language :: Python :: 3.6
Classifier: Programming Language :: Python :: 3.7
Classifier: Programming Language :: Python :: 3.8
Classifier: Programming Language :: Python :: 3.9
Classifier: Programming Language :: Python :: 3.10
Classifier: Topic :: Scientific/Engineering :: Bio-Informatics
Classifier: Topic :: Scientific/Engineering :: Visualization
Requires-Python: >=3.6
License-File: LICENSE
Requires-Dist: anndata
Requires-Dist: apted
Requires-Dist: biopython
Requires-Dist: click
Requires-Dist: cython
Requires-Dist: cyvcf2
Requires-Dist: ete3
Requires-Dist: ipython
Requires-Dist: joblib
Requires-Dist: matplotlib
Requires-Dist: mudata
Requires-Dist: natsort
Requires-Dist: networkx (<=2.8.3)
Requires-Dist: numba
Requires-Dist: numpy
Requires-Dist: pandas
Requires-Dist: pybnb
Requires-Dist: pydot
Requires-Dist: python-sat
Requires-Dist: pyyaml
Requires-Dist: scanpy
Requires-Dist: scikit-learn
Requires-Dist: scipy
Requires-Dist: seaborn
Requires-Dist: termcolor
Requires-Dist: tqdm
Provides-Extra: dev
Requires-Dist: black (==20.8b1) ; extra == 'dev'
Requires-Dist: pre-commit (==2.9.3) ; extra == 'dev'
Requires-Dist: isort (>=5.7.0) ; extra == 'dev'
Requires-Dist: pytest-cov ; extra == 'dev'
Provides-Extra: docs
Requires-Dist: memory-profiler (>=0.57.0) ; extra == 'docs'
Requires-Dist: nbsphinx (<0.8.7,>=0.8.6) ; extra == 'docs'
Requires-Dist: pyenchant (>=3.1.1) ; extra == 'docs'
Requires-Dist: pypandoc ; extra == 'docs'
Requires-Dist: requests ; extra == 'docs'
Requires-Dist: sphinx (<4.0.3,>=4) ; extra == 'docs'
Requires-Dist: sphinx-autodoc-annotation ; extra == 'docs'
Requires-Dist: sphinx-autodoc-typehints (>=1.10.3) ; extra == 'docs'
Requires-Dist: sphinx-click (>=3.0.1) ; extra == 'docs'
Requires-Dist: sphinx-paramlinks ; extra == 'docs'
Requires-Dist: sphinx-copybutton ; extra == 'docs'
Requires-Dist: sphinx-gallery (>=0.8.2) ; extra == 'docs'
Requires-Dist: sphinx-last-updated-by-git ; extra == 'docs'
Requires-Dist: sphinx-rtd-theme ; extra == 'docs'
Requires-Dist: sphinxcontrib-bibtex (>=2.1.0) ; extra == 'docs'
Requires-Dist: sphinxcontrib-spelling ; extra == 'docs'
